bus_queue/__init__.py
bus_queue/assync_bus.py
bus_queue/backend/memory/assync_bus.py
bus_queue/backend/memory/bus.py
bus_queue/backend/rabbit/assync_bus.py
bus_queue/backend/rabbit/bus.py
bus_queue/bus.py
bus_queue-0.5.4.dist-info/METADATA
bus_queue-0.5.4.dist-info/WHEEL
bus_queue-0.5.4.dist-info/RECORD
