Metadata-Version: 2.1
Name: bus_queue
Version: 0.5.4
Summary: 
Author: Gonzalo Ayuso
Author-email: gonzalo123@gmail.com
Requires-Python: >=3.9,<4.0
Classifier: Programming Language :: Python :: 3
Classifier: Programming Language :: Python :: 3.9
Classifier: Programming Language :: Python :: 3.10
Classifier: Programming Language :: Python :: 3.11
Classifier: Programming Language :: Python :: 3.12
Provides-Extra: async
Provides-Extra: sync
Requires-Dist: jsonencoder-gonzalo123 (>=1.1.0,<2.0.0)
